{
	"animations": [
		{
			"loop": false,
			"offsets": [
				410,
				560
			],
			"anim": "idle",
			"fps": 24,
			"name": "idle",
			"indices": []
		},
		{
			"loop": false,
			"offsets": [
				542,
				558
			],
			"anim": "singLEFT",
			"fps": 24,
			"name": "left",
			"indices": []
		},
		{
			"offsets": [
				450,
				550
			],
			"loop": false,
			"fps": 24,
			"anim": "singDOWN",
			"indices": [],
			"name": "down"
		},
		{
			"loop": false,
			"offsets": [
				450,
				604
			],
			"anim": "singUP",
			"fps": 24,
			"name": "up",
			"indices": []
		},
		{
			"offsets": [
				428,
				650
			],
			"loop": false,
			"fps": 24,
			"anim": "singRIGHT",
			"indices": [],
			"name": "right"
		}
	],
	"no_antialiasing": true,
	"image": "characters/v2/Pissey",
	"position": [
		600,
		650
	],
	"healthicon": "v2/pissey",
	"flip_x": false,
	"healthbar_colors": [
		247,
		242,
		49
	],
	"camera_position": [
		-460,
		-600
	],
	"sing_duration": 6.1,
	"scale": 1.6
}