{
	"animations": [
		{
			"loop": false,
			"offsets": [
				0,
				0
			],
			"anim": "idle",
			"fps": 24,
			"name": "BF idle dance",
			"indices": []
		},
		{
			"loop": false,
			"offsets": [
				-8,
				-2
			],
			"anim": "singLEFT",
			"fps": 24,
			"name": "BF NOTE LEFT0",
			"indices": []
		},
		{
			"loop": false,
			"offsets": [
				75,
				-25
			],
			"anim": "singDOWN",
			"fps": 24,
			"name": "BF NOTE DOWN0",
			"indices": []
		},
		{
			"loop": false,
			"offsets": [
				35,
				64
			],
			"anim": "singUP",
			"fps": 24,
			"name": "BF NOTE UP0",
			"indices": []
		},
		{
			"loop": false,
			"offsets": [
				31,
				-8
			],
			"anim": "singRIGHT",
			"fps": 24,
			"name": "BF NOTE RIGHT0",
			"indices": []
		},
		{
			"loop": false,
			"offsets": [
				-4,
				-3
			],
			"anim": "singLEFTmiss",
			"fps": 24,
			"name": "BF NOTE LEFT MISS",
			"indices": []
		},
		{
			"loop": false,
			"offsets": [
				76,
				-21
			],
			"anim": "singDOWNmiss",
			"fps": 24,
			"name": "BF NOTE DOWN MISS",
			"indices": []
		},
		{
			"loop": false,
			"offsets": [
				34,
				62
			],
			"anim": "singUPmiss",
			"fps": 24,
			"name": "BF NOTE UP MISS",
			"indices": []
		},
		{
			"loop": false,
			"offsets": [
				39,
				-7
			],
			"anim": "singRIGHTmiss",
			"fps": 24,
			"name": "BF NOTE RIGHT MISS",
			"indices": []
		},
		{
			"loop": false,
			"offsets": [
				26,
				2
			],
			"anim": "hey",
			"fps": 24,
			"name": "BF HEY",
			"indices": []
		},
		{
			"loop": false,
			"offsets": [
				88,
				0
			],
			"anim": "hurt",
			"fps": 24,
			"name": "BF hit",
			"indices": []
		},
		{
			"loop": true,
			"offsets": [
				4,
				-1
			],
			"anim": "scared",
			"fps": 24,
			"name": "BF idle shaking",
			"indices": []
		},
		{
			"loop": false,
			"offsets": [
				59,
				-39
			],
			"anim": "dodge",
			"fps": 24,
			"name": "boyfriend dodge",
			"indices": []
		},
		{
			"loop": false,
			"offsets": [
				192,
				247
			],
			"anim": "attack",
			"fps": 24,
			"name": "boyfriend attack",
			"indices": []
		}
	],
	"no_antialiasing": false,
	"image": "characters/TRISTAN",
	"position": [
		0,
		350
	],
	"healthicon": "tristan",
	"flip_x": true,
	"healthbar_colors": [
		255,
		19,
		15
	],
	"camera_position": [
		0,
		0
	],
	"sing_duration": 4,
	"scale": 1
}